MANIFEST.in
setup.py
gale/__init__.py
gale/autoreload.py
gale/cache.py
gale/config.py
gale/coroutine.py
gale/e.py
gale/escape.py
gale/files.py
gale/http.py
gale/httpconnection.py
gale/iosocket.py
gale/ipc.py
gale/log.py
gale/py_ver.py
gale/restapi.py
gale/running.py
gale/server.py
gale/session.py
gale/stream.py
gale/template.py
gale/utils.py
gale/web.py
gale/websocket.py
gale/static/bootstrap/css/bootstrap-theme.css
gale/static/bootstrap/css/bootstrap-theme.css.map
gale/static/bootstrap/css/bootstrap-theme.min.css
gale/static/bootstrap/css/bootstrap.css
gale/static/bootstrap/css/bootstrap.css.map
gale/static/bootstrap/css/bootstrap.min.css
gale/static/bootstrap/fonts/glyphicons-halflings-regular.eot
gale/static/bootstrap/fonts/glyphicons-halflings-regular.svg
gale/static/bootstrap/fonts/glyphicons-halflings-regular.ttf
gale/static/bootstrap/fonts/glyphicons-halflings-regular.woff
gale/static/bootstrap/fonts/glyphicons-halflings-regular.woff2
gale/static/bootstrap/js/bootstrap.js
gale/static/bootstrap/js/bootstrap.min.js
gale/static/bootstrap/js/npm.js
gale/static/css/debug.css
gale/static/js/angular.min.js
gale/static/js/debug.es6.js
gale/static/js/debug.js
gale/static/js/jquery.js
gale/template/db_table.html
gale/template/debug_wrap.html
gale/template/doc.html
gale/template/files.html
gale/wsgi/__init__.py
gale/wsgi/http.py
gale/wsgi/stream.py
gale/wsgi/web.py
gale_web.egg-info/PKG-INFO
gale_web.egg-info/SOURCES.txt
gale_web.egg-info/dependency_links.txt
gale_web.egg-info/requires.txt
gale_web.egg-info/top_level.txt