Metadata-Version: 1.0
Name: gale-web
Version: 4.3
Summary: a web framework like tornado
Home-page: https://github.com/lujinda/gale
Author: tuxpy
Author-email: UNKNOWN
License: UNKNOWN
Platform: UNKNOWN
